siliconmetatrader5/__init__.py
siliconmetatrader5/__main__.py
siliconmetatrader5/server.py
siliconmetatrader5-1.1.0.dist-info/licenses/LICENSE
siliconmetatrader5-1.1.0.dist-info/METADATA
siliconmetatrader5-1.1.0.dist-info/WHEEL
siliconmetatrader5-1.1.0.dist-info/top_level.txt
siliconmetatrader5-1.1.0.dist-info/RECORD
