Metadata-Version: 2.4
Name: siliconmetatrader5
Version: 1.1.0
Summary: MetaTrader5 for Apple Silicon (M1/M2/M3) via Docker
Author-email: Bahadir Umut Iscimen <buiscimen@gmail.com>
License: MIT
Project-URL: Homepage, https://github.com/buiscimen/siliconmetatrader5
Project-URL: Repository, https://github.com/buiscimen/siliconmetatrader5
Project-URL: Issues, https://github.com/buiscimen/siliconmetatrader5/issues
Keywords: metatrader5,mt5,trading,apple silicon,docker
Classifier: Development Status :: 4 - Beta
Classifier: Intended Audience :: Developers
Classifier: Intended Audience :: Financial and Insurance Industry
Classifier: License :: OSI Approved :: MIT License
Classifier: Operating System :: MacOS
Classifier: Programming Language :: Python :: 3
Classifier: Programming Language :: Python :: 3.9
Classifier: Programming Language :: Python :: 3.10
Classifier: Programming Language :: Python :: 3.11
Classifier: Programming Language :: Python :: 3.12
Classifier: Programming Language :: Python :: 3.13
Classifier: Topic :: Office/Business :: Financial :: Investment
Requires-Python: >=3.9
License-File: LICENSE
Requires-Dist: rpyc>=5.0.0
Dynamic: license-file
